lindap/__init__.py
lindap/classes.py
lindap/pydap.py
lindap/querybuilder.py
lindap/util.py
pydap/__init__.py
pydap/classes.py
pydap/pydap.py
pydap/querybuilder.py
pydap/util.py
linux_activedirectory-0.0.11.dist-info/LICENSE
linux_activedirectory-0.0.11.dist-info/METADATA
linux_activedirectory-0.0.11.dist-info/WHEEL
linux_activedirectory-0.0.11.dist-info/top_level.txt
linux_activedirectory-0.0.11.dist-info/RECORD
