Metadata-Version: 2.1
Name: linux-activedirectory
Version: 0.0.11
Summary: An LDAP wrapper designed to allow basic Active Directory automation from Linux
Home-page: UNKNOWN
License: UNKNOWN
Platform: UNKNOWN
Classifier: Programming Language :: Python :: 3
Classifier: Programming Language :: Python :: 3.6
Classifier: License :: OSI Approved :: GNU General Public License v3 or later (GPLv3+)
Classifier: Operating System :: POSIX :: Linux
Classifier: Topic :: System :: Systems Administration :: Authentication/Directory :: LDAP
Classifier: Topic :: System :: Systems Administration :: Authentication/Directory
Classifier: Topic :: System :: Systems Administration
Requires-Dist: python-ldap (~=3.3)
Provides-Extra: dev
Requires-Dist: colorama (==0.4.3) ; extra == 'dev'
